MANIFEST.in
README.txt
setup.py
bin/centersearch
bin/installdronedeps
bin/testpredictor
bin/trigger
distdrone/__init__.py
distdrone/text.py
distdrone.egg-info/PKG-INFO
distdrone.egg-info/SOURCES.txt
distdrone.egg-info/dependency_links.txt
distdrone.egg-info/not-zip-safe
distdrone.egg-info/top_level.txt
distdrone/motion/__init__.py
distdrone/motion/gears.py