Metadata-Version: 1.0
Name: distdrone
Version: 1.20
Summary: package to drive parallel drone swarm
Home-page: http://github.com/isaacrob/paradrone
Author: Isaac Robinson
Author-email: isaacrob@me.com
License: MIT
Platform: UNKNOWN
